{
  "objectives": [
    {
      "id": "1",
      "objective": "Build a software team",
      "keyResults": [
        {
          "title": "Get 5 Frontend engineers",
          "initialValue": 0,
          "currentValue": 2,
          "targetValue": 5,
          "metrics": "engineers"
        },
        {
          "title": "Get 5 Backend engineers",
          "initialValue": 0,
          "currentValue": 1,
          "targetValue": 5,
          "metrics": "engineers"
        }
      ]
    },
    {
      "objective": "dvgf",
      "keyResults": [
        {
          "title": "",
          "initialValue": 0,
          "currentValue": 0,
          "targetValue": 0,
          "metrics": ""
        }
      ],
      "id": "0e38"
    },
    {
      "id": "4381",
      "objective": "sdasd",
      "keyResults": [
        {
          "title": "asdsdsadsadsdsdsadsadsadsadddds",
          "initialValue": 0,
          "currentValue": 0,
          "targetValue": 0,
          "metrics": ""
        }
      ]
    }
  ]
}